<?xml version="1.0" encoding="UTF-8" ?>
<datascrolls>
  <datascroll>
    <ユーザーNO>1001</ユーザーNO>
    <姓>栗原</姓>
    <名>鑑</名>
    <姓_カタカナ>クリハラ</姓_カタカナ>
    <名_カタカナ>アキラ</名_カタカナ>
    <性別>男</性別>
    <電話番号>0481624636</電話番号>
    <メールアドレス>akurihara@rekfhq.ufm</メールアドレス>
    <郵便番号>357-0064</郵便番号>
    <現住所_県>埼玉県</現住所_県>
    <現住所_市>飯能市</現住所_市>
    <生年月日>1987/09/06</生年月日>
    <年齢>27</年齢>
    <出身地>宮崎県</出身地>
    <血液型>B</血液型>
  </datascroll>
  <datascroll>
    <ユーザーNO>1002</ユーザーNO>
    <姓>長崎</姓>
    <名>玲菜</名>
    <姓_カタカナ>ナガサキ</姓_カタカナ>
    <名_カタカナ>レナ</名_カタカナ>
    <性別>女</性別>
    <電話番号>0998885527</電話番号>
    <メールアドレス>rena649@mdoxiw.me</メールアドレス>
    <郵便番号>893-1204</郵便番号>
    <現住所_県>鹿児島県</現住所_県>
    <現住所_市>肝属郡肝付町</現住所_市>
    <生年月日>1981/10/15</生年月日>
    <年齢>33</年齢>
    <出身地>奈良県</出身地>
    <血液型>O</血液型>
  </datascroll>
  <datascroll>
    <ユーザーNO>1003</ユーザーNO>
    <姓>杉村</姓>
    <名>康司</名>
    <姓_カタカナ>スギムラ</姓_カタカナ>
    <名_カタカナ>コウジ</名_カタカナ>
    <性別>男</性別>
    <電話番号>0968411320</電話番号>
    <メールアドレス>q-uncqldlckouji12415@apvdmjadb.zi.lyn</メールアドレス>
    <郵便番号>861-0563</郵便番号>
    <現住所_県>熊本県</現住所_県>
    <現住所_市>山鹿市</現住所_市>
    <生年月日>1960/08/20</生年月日>
    <年齢>54</年齢>
    <出身地>青森県</出身地>
    <血液型>O</血液型>
  </datascroll>
  <datascroll>
    <ユーザーNO>1004</ユーザーNO>
    <姓>古市</姓>
    <名>克巳</名>
    <姓_カタカナ>フルイチ</姓_カタカナ>
    <名_カタカナ>カツミ</名_カタカナ>
    <性別>男</性別>
    <電話番号>0778585212</電話番号>
    <メールアドレス>katsumi50581@nlgkajo.nk.qvg</メールアドレス>
    <郵便番号>606-8405</郵便番号>
    <現住所_県>京都府</現住所_県>
    <現住所_市>京都市左京区</現住所_市>
    <生年月日>1980/07/31</生年月日>
    <年齢>35</年齢>
    <出身地>神奈川県</出身地>
    <血液型>B</血液型>
  </datascroll>
  <datascroll>
    <ユーザーNO>1005</ユーザーNO>
    <姓>青柳</姓>
    <名>杏奈</名>
    <姓_カタカナ>アオヤギ</姓_カタカナ>
    <名_カタカナ>アンナ</名_カタカナ>
    <性別>女</性別>
    <電話番号>0550054469</電話番号>
    <メールアドレス>Amna_Aoyagi@vfoaxfyplx.yccf.oxn</メールアドレス>
    <郵便番号>417-0046</郵便番号>
    <現住所_県>静岡県</現住所_県>
    <現住所_市>富士市</現住所_市>
    <生年月日>1986/01/10</生年月日>
    <年齢>29</年齢>
    <出身地>青森県</出身地>
    <血液型>A</血液型>
  </datascroll>
  <datascroll>
    <ユーザーNO>1006</ユーザーNO>
    <姓>早坂</姓>
    <名>敏彦</名>
    <姓_カタカナ>ハヤサカ</姓_カタカナ>
    <名_カタカナ>トシヒコ</名_カタカナ>
    <性別>男</性別>
    <電話番号>0184074299</電話番号>
    <メールアドレス>qqkbtarhtoshihiko82551@jvvyaw.axuv.rt</メールアドレス>
    <郵便番号>015-0856</郵便番号>
    <現住所_県>秋田県</現住所_県>
    <現住所_市>由利本荘市</現住所_市>
    <生年月日>1983/09/17</生年月日>
    <年齢>31</年齢>
    <出身地>宮城県</出身地>
    <血液型>O</血液型>
  </datascroll>
  <datascroll>
    <ユーザーNO>1007</ユーザーNO>
    <姓>小平</姓>
    <名>夏実</名>
    <姓_カタカナ>コダイラ</姓_カタカナ>
    <名_カタカナ>ナツミ</名_カタカナ>
    <性別>女</性別>
    <電話番号>0444222748</電話番号>
    <メールアドレス>natsumi56528@lzzpem.on</メールアドレス>
    <郵便番号>220-0203</郵便番号>
    <現住所_県>神奈川県</現住所_県>
    <現住所_市>相模原市</現住所_市>
    <生年月日>1957/02/01</生年月日>
    <年齢>58</年齢>
    <出身地>大分県</出身地>
    <血液型>O</血液型>
  </datascroll>
  <datascroll>
    <ユーザーNO>1008</ユーザーNO>
    <姓>伊沢</姓>
    <名>信玄</名>
    <姓_カタカナ>イザワ</姓_カタカナ>
    <名_カタカナ>シンゲン</名_カタカナ>
    <性別>男</性別>
    <電話番号>0475908216</電話番号>
    <メールアドレス>shingenizawa@ctqlvdtis.ffzu.ht</メールアドレス>
    <郵便番号>338-0011</郵便番号>
    <現住所_県>埼玉県</現住所_県>
    <現住所_市>さいたま市中央区</現住所_市>
    <生年月日>1982/12/05</生年月日>
    <年齢>32</年齢>
    <出身地>愛知県</出身地>
    <血液型>A</血液型>
  </datascroll>
  <datascroll>
    <ユーザーNO>1009</ユーザーNO>
    <姓>島</姓>
    <名>怜子</名>
    <姓_カタカナ>シマ</姓_カタカナ>
    <名_カタカナ>レイコ</名_カタカナ>
    <性別>女</性別>
    <電話番号>0536291996</電話番号>
    <メールアドレス>reikoshima@fjdwbqbi.wq</メールアドレス>
    <郵便番号>444-3432</郵便番号>
    <現住所_県>愛知県</現住所_県>
    <現住所_市>岡崎市</現住所_市>
    <生年月日>1986/03/31</生年月日>
    <年齢>29</年齢>
    <出身地>山形県</出身地>
    <血液型>A</血液型>
  </datascroll>
  <datascroll>
    <ユーザーNO>1010</ユーザーNO>
    <姓>倉橋</姓>
    <名>泰佑</名>
    <姓_カタカナ>クラハシ</姓_カタカナ>
    <名_カタカナ>タイスケ</名_カタカナ>
    <性別>男</性別>
    <電話番号>0875642545</電話番号>
    <メールアドレス>taisuke419@ivle.hzk</メールアドレス>
    <郵便番号>763-0111</郵便番号>
    <現住所_県>香川県</現住所_県>
    <現住所_市>丸亀市</現住所_市>
    <生年月日>1969/12/11</生年月日>
    <年齢>45</年齢>
    <出身地>千葉県</出身地>
    <血液型>B</血液型>
  </datascroll>
  <datascroll>
    <ユーザーNO>1011</ユーザーNO>
    <姓>西口</姓>
    <名>菊男</名>
    <姓_カタカナ>ニシグチ</姓_カタカナ>
    <名_カタカナ>キクオ</名_カタカナ>
    <性別>男</性別>
    <電話番号>0980974298</電話番号>
    <メールアドレス>onishiguchi@cyebw.ffq</メールアドレス>
    <郵便番号>906-0303</郵便番号>
    <現住所_県>沖縄県</現住所_県>
    <現住所_市>宮古島市</現住所_市>
    <生年月日>1982/01/04</生年月日>
    <年齢>33</年齢>
    <出身地>北海道</出身地>
    <血液型>A</血液型>
  </datascroll>
  <datascroll>
    <ユーザーNO>1012</ユーザーNO>
    <姓>小林</姓>
    <名>眞</名>
    <姓_カタカナ>コバヤシ</姓_カタカナ>
    <名_カタカナ>マコト</名_カタカナ>
    <性別>男</性別>
    <電話番号>0267571124</電話番号>
    <メールアドレス>makoto0590@mhnkes.qjo</メールアドレス>
    <郵便番号>385-0053</郵便番号>
    <現住所_県>長野県</現住所_県>
    <現住所_市>佐久市</現住所_市>
    <生年月日>1987/12/01</生年月日>
    <年齢>27</年齢>
    <出身地>山形県</出身地>
    <血液型>A</血液型>
  </datascroll>
  <datascroll>
    <ユーザーNO>1013</ユーザーNO>
    <姓>岩沢</姓>
    <名>文平</名>
    <姓_カタカナ>イワサワ</姓_カタカナ>
    <名_カタカナ>ブンペイ</名_カタカナ>
    <性別>男</性別>
    <電話番号>0747842844</電話番号>
    <メールアドレス>bumpei7455@mtvnveiil.kj</メールアドレス>
    <郵便番号>634-0052</郵便番号>
    <現住所_県>奈良県</現住所_県>
    <現住所_市>橿原市</現住所_市>
    <生年月日>1958/12/27</生年月日>
    <年齢>56</年齢>
    <出身地>福島県</出身地>
    <血液型>O</血液型>
  </datascroll>
  <datascroll>
    <ユーザーNO>1014</ユーザーNO>
    <姓>外山</姓>
    <名>新平</名>
    <姓_カタカナ>ソトヤマ</姓_カタカナ>
    <名_カタカナ>シンペイ</名_カタカナ>
    <性別>男</性別>
    <電話番号>0920305746</電話番号>
    <メールアドレス>shimpei8955@vikyap.wpo</メールアドレス>
    <郵便番号>811-5113</郵便番号>
    <現住所_県>長崎県</現住所_県>
    <現住所_市>壱岐市</現住所_市>
    <生年月日>1984/03/23</生年月日>
    <年齢>31</年齢>
    <出身地>熊本県</出身地>
    <血液型>B</血液型>
  </datascroll>
  <datascroll>
    <ユーザーNO>1015</ユーザーNO>
    <姓>奥野</姓>
    <名>勝哉</名>
    <姓_カタカナ>オクノ</姓_カタカナ>
    <名_カタカナ>カツヤ</名_カタカナ>
    <性別>男</性別>
    <電話番号>0925278763</電話番号>
    <メールアドレス>katsuya031@nlilwcgf.pl.hjn</メールアドレス>
    <郵便番号>807-1121</郵便番号>
    <現住所_県>福岡県</現住所_県>
    <現住所_市>北九州市八幡西区</現住所_市>
    <生年月日>1958/05/13</生年月日>
    <年齢>57</年齢>
    <出身地>香川県</出身地>
    <血液型>A</血液型>
  </datascroll>
  <datascroll>
    <ユーザーNO>1016</ユーザーNO>
    <姓>吾妻</姓>
    <名>高志</名>
    <姓_カタカナ>アズマ</姓_カタカナ>
    <名_カタカナ>タカシ</名_カタカナ>
    <性別>男</性別>
    <電話番号>0952582142</電話番号>
    <メールアドレス>e=tnlhqfzjtakashi382@aldqri.wu</メールアドレス>
    <郵便番号>849-1611</郵便番号>
    <現住所_県>佐賀県</現住所_県>
    <現住所_市>藤津郡太良町</現住所_市>
    <生年月日>1967/03/25</生年月日>
    <年齢>48</年齢>
    <出身地>沖縄県</出身地>
    <血液型>A</血液型>
  </datascroll>
  <datascroll>
    <ユーザーNO>1017</ユーザーNO>
    <姓>福岡</姓>
    <名>梢</名>
    <姓_カタカナ>フクオカ</姓_カタカナ>
    <名_カタカナ>コズエ</名_カタカナ>
    <性別>女</性別>
    <電話番号>0761172962</電話番号>
    <メールアドレス>Kozue_Fukuoka@rnmnrenb.du.ssg</メールアドレス>
    <郵便番号>929-0224</郵便番号>
    <現住所_県>石川県</現住所_県>
    <現住所_市>白山市</現住所_市>
    <生年月日>1988/04/11</生年月日>
    <年齢>27</年齢>
    <出身地>香川県</出身地>
    <血液型>A</血液型>
  </datascroll>
  <datascroll>
    <ユーザーNO>1018</ユーザーNO>
    <姓>岩城</姓>
    <名>正志</名>
    <姓_カタカナ>イワキ</姓_カタカナ>
    <名_カタカナ>マサシ</名_カタカナ>
    <性別>男</性別>
    <電話番号>0970858045</電話番号>
    <メールアドレス>masashi71313@baommudefr.jaj</メールアドレス>
    <郵便番号>879-1121</郵便番号>
    <現住所_県>大分県</現住所_県>
    <現住所_市>宇佐市</現住所_市>
    <生年月日>1970/06/15</生年月日>
    <年齢>45</年齢>
    <出身地>静岡県</出身地>
    <血液型>B</血液型>
  </datascroll>
  <datascroll>
    <ユーザーNO>1019</ユーザーNO>
    <姓>上岡</姓>
    <名>隆吾</名>
    <姓_カタカナ>カミオカ</姓_カタカナ>
    <名_カタカナ>リュウゴ</名_カタカナ>
    <性別>男</性別>
    <電話番号>0580275132</電話番号>
    <メールアドレス>ryuugokamioka@rtgsxnoj.wby</メールアドレス>
    <郵便番号>503-0302</郵便番号>
    <現住所_県>岐阜県</現住所_県>
    <現住所_市>海津市</現住所_市>
    <生年月日>1986/03/01</生年月日>
    <年齢>29</年齢>
    <出身地>秋田県</出身地>
    <血液型>A</血液型>
  </datascroll>
  <datascroll>
    <ユーザーNO>1020</ユーザーNO>
    <姓>園田</姓>
    <名>重治</名>
    <姓_カタカナ>ソノダ</姓_カタカナ>
    <名_カタカナ>シゲハル</名_カタカナ>
    <性別>男</性別>
    <電話番号>0173303612</電話番号>
    <メールアドレス>shigeharu215@kgiajkuxt.xy.sw</メールアドレス>
    <郵便番号>036-0316</郵便番号>
    <現住所_県>青森県</現住所_県>
    <現住所_市>黒石市</現住所_市>
    <生年月日>1987/03/18</生年月日>
    <年齢>28</年齢>
    <出身地>秋田県</出身地>
    <血液型>O</血液型>
  </datascroll>
  <datascroll>
    <ユーザーNO>1021</ユーザーNO>
    <姓>飛田</姓>
    <名>京子</名>
    <姓_カタカナ>トビタ</姓_カタカナ>
    <名_カタカナ>キョウコ</名_カタカナ>
    <性別>女</性別>
    <電話番号>0437039361</電話番号>
    <メールアドレス>kyouko3583@btsqiu.gyz</メールアドレス>
    <郵便番号>270-1123</郵便番号>
    <現住所_県>千葉県</現住所_県>
    <現住所_市>我孫子市</現住所_市>
    <生年月日>1971/04/19</生年月日>
    <年齢>44</年齢>
    <出身地>兵庫県</出身地>
    <血液型>A</血液型>
  </datascroll>
  <datascroll>
    <ユーザーNO>1022</ユーザーNO>
    <姓>井本</姓>
    <名>孝司</名>
    <姓_カタカナ>イモト</姓_カタカナ>
    <名_カタカナ>タカシ</名_カタカナ>
    <性別>男</性別>
    <電話番号>0882805161</電話番号>
    <メールアドレス>takashi_imoto@pivsynegj.jbche.mvx</メールアドレス>
    <郵便番号>781-6448</郵便番号>
    <現住所_県>高知県</現住所_県>
    <現住所_市>安芸郡北川村</現住所_市>
    <生年月日>1981/01/27</生年月日>
    <年齢>34</年齢>
    <出身地>北海道</出身地>
    <血液型>AB</血液型>
  </datascroll>
  <datascroll>
    <ユーザーNO>1023</ユーザーNO>
    <姓>岡田</姓>
    <名>柑奈</名>
    <姓_カタカナ>オカダ</姓_カタカナ>
    <名_カタカナ>カンナ</名_カタカナ>
    <性別>女</性別>
    <電話番号>0744440245</電話番号>
    <メールアドレス>kamnaokada@bxseaw.cws</メールアドレス>
    <郵便番号>630-8037</郵便番号>
    <現住所_県>奈良県</現住所_県>
    <現住所_市>奈良市</現住所_市>
    <生年月日>1987/02/07</生年月日>
    <年齢>28</年齢>
    <出身地>山口県</出身地>
    <血液型>A</血液型>
  </datascroll>
  <datascroll>
    <ユーザーNO>1024</ユーザーNO>
    <姓>瀬川</姓>
    <名>昌幸</名>
    <姓_カタカナ>セガワ</姓_カタカナ>
    <名_カタカナ>マサユキ</名_カタカナ>
    <性別>男</性別>
    <電話番号>0574705838</電話番号>
    <メールアドレス>isegawa@ftycqku.lnhx.uk</メールアドレス>
    <郵便番号>509-4253</郵便番号>
    <現住所_県>岐阜県</現住所_県>
    <現住所_市>飛騨市</現住所_市>
    <生年月日>1958/12/04</生年月日>
    <年齢>56</年齢>
    <出身地>富山県</出身地>
    <血液型>A</血液型>
  </datascroll>
  <datascroll>
    <ユーザーNO>1025</ユーザーNO>
    <姓>柳川</姓>
    <名>倫子</名>
    <姓_カタカナ>ヤナガワ</姓_カタカナ>
    <名_カタカナ>ミチコ</名_カタカナ>
    <性別>女</性別>
    <電話番号>0987734611</電話番号>
    <メールアドレス>oyanagawa@vdohwtfz.ken</メールアドレス>
    <郵便番号>905-0701</郵便番号>
    <現住所_県>沖縄県</現住所_県>
    <現住所_市>島尻郡伊平屋村</現住所_市>
    <生年月日>1962/02/16</生年月日>
    <年齢>53</年齢>
    <出身地>大分県</出身地>
    <血液型>A</血液型>
  </datascroll>
  <datascroll>
    <ユーザーNO>1026</ユーザーNO>
    <姓>平本</姓>
    <名>光</名>
    <姓_カタカナ>ヒラモト</姓_カタカナ>
    <名_カタカナ>ヒカル</名_カタカナ>
    <性別>女</性別>
    <電話番号>0867076387</電話番号>
    <メールアドレス>hikaru0356@pzqjsbp.ryigd.hy</メールアドレス>
    <郵便番号>719-2723</郵便番号>
    <現住所_県>岡山県</現住所_県>
    <現住所_市>新見市</現住所_市>
    <生年月日>1995/02/09</生年月日>
    <年齢>20</年齢>
    <出身地>埼玉県</出身地>
    <血液型>B</血液型>
  </datascroll>
  <datascroll>
    <ユーザーNO>1027</ユーザーNO>
    <姓>荒井</姓>
    <名>俊哉</名>
    <姓_カタカナ>アライ</姓_カタカナ>
    <名_カタカナ>トシヤ</名_カタカナ>
    <性別>男</性別>
    <電話番号>0261291855</電話番号>
    <メールアドレス>toshiya487@zbjqx.wcecx.yg</メールアドレス>
    <郵便番号>388-8005</郵便番号>
    <現住所_県>長野県</現住所_県>
    <現住所_市>長野市</現住所_市>
    <生年月日>1978/11/07</生年月日>
    <年齢>36</年齢>
    <出身地>岡山県</出身地>
    <血液型>O</血液型>
  </datascroll>
  <datascroll>
    <ユーザーNO>1028</ユーザーNO>
    <姓>沼田</姓>
    <名>謙三</名>
    <姓_カタカナ>ヌマタ</姓_カタカナ>
    <名_カタカナ>ケンゾウ</名_カタカナ>
    <性別>男</性別>
    <電話番号>0880423106</電話番号>
    <メールアドレス>kenzou_numata@kznjtkpb.yl</メールアドレス>
    <郵便番号>779-0108</郵便番号>
    <現住所_県>徳島県</現住所_県>
    <現住所_市>板野郡板野町</現住所_市>
    <生年月日>1994/08/10</生年月日>
    <年齢>20</年齢>
    <出身地>群馬県</出身地>
    <血液型>O</血液型>
  </datascroll>
  <datascroll>
    <ユーザーNO>1029</ユーザーNO>
    <姓>田口</姓>
    <名>秀之</名>
    <姓_カタカナ>タグチ</姓_カタカナ>
    <名_カタカナ>ヒデユキ</名_カタカナ>
    <性別>男</性別>
    <電話番号>0301588762</電話番号>
    <メールアドレス>itaguchi@oyzb.fse</メールアドレス>
    <郵便番号>111-0041</郵便番号>
    <現住所_県>東京都</現住所_県>
    <現住所_市>台東区</現住所_市>
    <生年月日>1990/08/19</生年月日>
    <年齢>24</年齢>
    <出身地>茨城県</出身地>
    <血液型>B</血液型>
  </datascroll>
  <datascroll>
    <ユーザーNO>1030</ユーザーNO>
    <姓>広川</姓>
    <名>忠正</名>
    <姓_カタカナ>ヒロカワ</姓_カタカナ>
    <名_カタカナ>タダマサ</名_カタカナ>
    <性別>男</性別>
    <電話番号>0232839979</電話番号>
    <メールアドレス>xng-qojtadamasa688@phgmdlfmmi.nqreb.nve</メールアドレス>
    <郵便番号>999-8437</郵便番号>
    <現住所_県>山形県</現住所_県>
    <現住所_市>飽海郡遊佐町</現住所_市>
    <生年月日>1988/10/12</生年月日>
    <年齢>26</年齢>
    <出身地>青森県</出身地>
    <血液型>O</血液型>
  </datascroll>
  <datascroll>
    <ユーザーNO>1031</ユーザーNO>
    <姓>渡部</姓>
    <名>真澄</名>
    <姓_カタカナ>ワタナベ</姓_カタカナ>
    <名_カタカナ>マスミ</名_カタカナ>
    <性別>女</性別>
    <電話番号>0629432332</電話番号>
    <メールアドレス>Masumi_Watanabe@twtbos.lhtqk.wnd</メールアドレス>
    <郵便番号>590-0155</郵便番号>
    <現住所_県>大阪府</現住所_県>
    <現住所_市>堺市南区</現住所_市>
    <生年月日>1984/03/25</生年月日>
    <年齢>31</年齢>
    <出身地>福井県</出身地>
    <血液型>O</血液型>
  </datascroll>
  <datascroll>
    <ユーザーNO>1032</ユーザーNO>
    <姓>石原</姓>
    <名>千枝子</名>
    <姓_カタカナ>イシハラ</姓_カタカナ>
    <名_カタカナ>チエコ</名_カタカナ>
    <性別>女</性別>
    <電話番号>0193866233</電話番号>
    <メールアドレス>ocmdkgcnmschieko88588@gyvoy.pov</メールアドレス>
    <郵便番号>028-8803</郵便番号>
    <現住所_県>岩手県</現住所_県>
    <現住所_市>九戸郡洋野町</現住所_市>
    <生年月日>1986/04/19</生年月日>
    <年齢>29</年齢>
    <出身地>青森県</出身地>
    <血液型>O</血液型>
  </datascroll>
  <datascroll>
    <ユーザーNO>1033</ユーザーNO>
    <姓>北野</姓>
    <名>博司</名>
    <姓_カタカナ>キタノ</姓_カタカナ>
    <名_カタカナ>ヒロシ</名_カタカナ>
    <性別>男</性別>
    <電話番号>025582894</電話番号>
    <メールアドレス>ikitano@azprse.drm.yok</メールアドレス>
    <郵便番号>959-2822</郵便番号>
    <現住所_県>新潟県</現住所_県>
    <現住所_市>胎内市</現住所_市>
    <生年月日>1961/01/05</生年月日>
    <年齢>54</年齢>
    <出身地>徳島県</出身地>
    <血液型>O</血液型>
  </datascroll>
  <datascroll>
    <ユーザーNO>1034</ユーザーNO>
    <姓>梶原</姓>
    <名>優那</名>
    <姓_カタカナ>カジワラ</姓_カタカナ>
    <名_カタカナ>ユウナ</名_カタカナ>
    <性別>女</性別>
    <電話番号>0921885834</電話番号>
    <メールアドレス>yuuna_kajiwara@aiwtuiw.uuq</メールアドレス>
    <郵便番号>800-0211</郵便番号>
    <現住所_県>福岡県</現住所_県>
    <現住所_市>北九州市小倉南区</現住所_市>
    <生年月日>1967/12/24</生年月日>
    <年齢>47</年齢>
    <出身地>岐阜県</出身地>
    <血液型>A</血液型>
  </datascroll>
  <datascroll>
    <ユーザーNO>1035</ユーザーNO>
    <姓>福本</姓>
    <名>里歩</名>
    <姓_カタカナ>フクモト</姓_カタカナ>
    <名_カタカナ>リホ</名_カタカナ>
    <性別>女</性別>
    <電話番号>0746904218</電話番号>
    <メールアドレス>riho48859@oyqacvztc.eorw.dvl</メールアドレス>
    <郵便番号>633-0014</郵便番号>
    <現住所_県>奈良県</現住所_県>
    <現住所_市>桜井市</現住所_市>
    <生年月日>1976/05/10</生年月日>
    <年齢>39</年齢>
    <出身地>新潟県</出身地>
    <血液型>A</血液型>
  </datascroll>
  <datascroll>
    <ユーザーNO>1036</ユーザーNO>
    <姓>岩下</姓>
    <名>栞奈</名>
    <姓_カタカナ>イワシタ</姓_カタカナ>
    <名_カタカナ>カンナ</名_カタカナ>
    <性別>女</性別>
    <電話番号>0773073837</電話番号>
    <メールアドレス>ieezqhvng==kamna699@nnxo.uax</メールアドレス>
    <郵便番号>605-0076</郵便番号>
    <現住所_県>京都府</現住所_県>
    <現住所_市>京都市東山区</現住所_市>
    <生年月日>1990/09/20</生年月日>
    <年齢>24</年齢>
    <出身地>秋田県</出身地>
    <血液型>O</血液型>
  </datascroll>
  <datascroll>
    <ユーザーNO>1037</ユーザーNO>
    <姓>二瓶</姓>
    <名>智恵子</名>
    <姓_カタカナ>ニヘイ</姓_カタカナ>
    <名_カタカナ>チエコ</名_カタカナ>
    <性別>女</性別>
    <電話番号>0192488316</電話番号>
    <メールアドレス>Chieko_Nihei@fxhekxvsz.becus.lh</メールアドレス>
    <郵便番号>028-0091</郵便番号>
    <現住所_県>岩手県</現住所_県>
    <現住所_市>久慈市</現住所_市>
    <生年月日>1965/07/12</生年月日>
    <年齢>50</年齢>
    <出身地>滋賀県</出身地>
    <血液型>A</血液型>
  </datascroll>
  <datascroll>
    <ユーザーNO>1038</ユーザーNO>
    <姓>前島</姓>
    <名>結月</名>
    <姓_カタカナ>マエジマ</姓_カタカナ>
    <名_カタカナ>ユヅキ</名_カタカナ>
    <性別>女</性別>
    <電話番号>0986487515</電話番号>
    <メールアドレス>kmgczoyuzuki9017@ewfzunictx.cwr</メールアドレス>
    <郵便番号>891-5204</郵便番号>
    <現住所_県>鹿児島県</現住所_県>
    <現住所_市>鹿児島郡十島村</現住所_市>
    <生年月日>1973/06/13</生年月日>
    <年齢>42</年齢>
    <出身地>山梨県</出身地>
    <血液型>AB</血液型>
  </datascroll>
  <datascroll>
    <ユーザーNO>1039</ユーザーNO>
    <姓>岸本</姓>
    <名>紗希</名>
    <姓_カタカナ>キシモト</姓_カタカナ>
    <名_カタカナ>サキ</名_カタカナ>
    <性別>女</性別>
    <電話番号>0859748456</電話番号>
    <メールアドレス>sakikishimoto@fzztjqs.vt</メールアドレス>
    <郵便番号>680-0725</郵便番号>
    <現住所_県>鳥取県</現住所_県>
    <現住所_市>八頭郡若桜町</現住所_市>
    <生年月日>1993/06/09</生年月日>
    <年齢>22</年齢>
    <出身地>大分県</出身地>
    <血液型>B</血液型>
  </datascroll>
  <datascroll>
    <ユーザーNO>1040</ユーザーNO>
    <姓>浜</姓>
    <名>絢菜</名>
    <姓_カタカナ>ハマ</姓_カタカナ>
    <名_カタカナ>アヤナ</名_カタカナ>
    <性別>女</性別>
    <電話番号>0299238651</電話番号>
    <メールアドレス>ayana_hama@cmnf.gi</メールアドレス>
    <郵便番号>319-1701</郵便番号>
    <現住所_県>茨城県</現住所_県>
    <現住所_市>北茨城市</現住所_市>
    <生年月日>1973/12/25</生年月日>
    <年齢>41</年齢>
    <出身地>奈良県</出身地>
    <血液型>O</血液型>
  </datascroll>
  <datascroll>
    <ユーザーNO>1041</ユーザーNO>
    <姓>宮原</姓>
    <名>広明</名>
    <姓_カタカナ>ミヤハラ</姓_カタカナ>
    <名_カタカナ>ヒロアキ</名_カタカナ>
    <性別>男</性別>
    <電話番号>0821116471</電話番号>
    <メールアドレス>hiroakimiyahara@zbmdmkxmwp.ffl</メールアドレス>
    <郵便番号>734-0003</郵便番号>
    <現住所_県>広島県</現住所_県>
    <現住所_市>広島市南区</現住所_市>
    <生年月日>1966/09/09</生年月日>
    <年齢>48</年齢>
    <出身地>秋田県</出身地>
    <血液型>AB</血液型>
  </datascroll>
  <datascroll>
    <ユーザーNO>1042</ユーザーNO>
    <姓>若林</姓>
    <名>敏子</名>
    <姓_カタカナ>ワカバヤシ</姓_カタカナ>
    <名_カタカナ>トシコ</名_カタカナ>
    <性別>女</性別>
    <電話番号>0555194887</電話番号>
    <メールアドレス>toshiko_wakabayashi@ljuatlio.vq</メールアドレス>
    <郵便番号>409-3601</郵便番号>
    <現住所_県>山梨県</現住所_県>
    <現住所_市>西八代郡市川三郷町</現住所_市>
    <生年月日>1971/07/17</生年月日>
    <年齢>44</年齢>
    <出身地>青森県</出身地>
    <血液型>O</血液型>
  </datascroll>
  <datascroll>
    <ユーザーNO>1043</ユーザーNO>
    <姓>高岡</姓>
    <名>俊章</名>
    <姓_カタカナ>タカオカ</姓_カタカナ>
    <名_カタカナ>トシアキ</名_カタカナ>
    <性別>男</性別>
    <電話番号>0537306300</電話番号>
    <メールアドレス>toshiaki_takaoka@gzia.jn</メールアドレス>
    <郵便番号>431-0441</郵便番号>
    <現住所_県>静岡県</現住所_県>
    <現住所_市>湖西市</現住所_市>
    <生年月日>1966/01/14</生年月日>
    <年齢>49</年齢>
    <出身地>北海道</出身地>
    <血液型>O</血液型>
  </datascroll>
  <datascroll>
    <ユーザーNO>1044</ユーザーNO>
    <姓>皆川</姓>
    <名>麗子</名>
    <姓_カタカナ>ミナガワ</姓_カタカナ>
    <名_カタカナ>レイコ</名_カタカナ>
    <性別>女</性別>
    <電話番号>0273560855</電話番号>
    <メールアドレス>reiko38255@rbtph.me</メールアドレス>
    <郵便番号>374-0037</郵便番号>
    <現住所_県>群馬県</現住所_県>
    <現住所_市>館林市</現住所_市>
    <生年月日>1983/10/02</生年月日>
    <年齢>31</年齢>
    <出身地>愛知県</出身地>
    <血液型>A</血液型>
  </datascroll>
  <datascroll>
    <ユーザーNO>1045</ユーザーNO>
    <姓>萩原</姓>
    <名>真吉</名>
    <姓_カタカナ>ハギワラ</姓_カタカナ>
    <名_カタカナ>シンキチ</名_カタカナ>
    <性別>男</性別>
    <電話番号>074408461</電話番号>
    <メールアドレス>shinkichihagiwara@pshv.xrvju.kjo</メールアドレス>
    <郵便番号>633-0315</郵便番号>
    <現住所_県>奈良県</現住所_県>
    <現住所_市>宇陀市</現住所_市>
    <生年月日>1991/04/04</生年月日>
    <年齢>24</年齢>
    <出身地>大阪府</出身地>
    <血液型>A</血液型>
  </datascroll>
  <datascroll>
    <ユーザーNO>1046</ユーザーNO>
    <姓>本多</姓>
    <名>沙希</名>
    <姓_カタカナ>ホンダ</姓_カタカナ>
    <名_カタカナ>サキ</名_カタカナ>
    <性別>女</性別>
    <電話番号>0438566836</電話番号>
    <メールアドレス>etkrearsaki31743@oneztwn.yug</メールアドレス>
    <郵便番号>270-1315</郵便番号>
    <現住所_県>千葉県</現住所_県>
    <現住所_市>印西市</現住所_市>
    <生年月日>1961/09/04</生年月日>
    <年齢>53</年齢>
    <出身地>山形県</出身地>
    <血液型>A</血液型>
  </datascroll>
  <datascroll>
    <ユーザーNO>1047</ユーザーNO>
    <姓>唐沢</姓>
    <名>文彦</名>
    <姓_カタカナ>カラサワ</姓_カタカナ>
    <名_カタカナ>フミヒコ</名_カタカナ>
    <性別>男</性別>
    <電話番号>0584879406</電話番号>
    <メールアドレス>fumihikokarasawa@oght.jl</メールアドレス>
    <郵便番号>501-3264</郵便番号>
    <現住所_県>岐阜県</現住所_県>
    <現住所_市>関市</現住所_市>
    <生年月日>1980/11/27</生年月日>
    <年齢>34</年齢>
    <出身地>大阪府</出身地>
    <血液型>O</血液型>
  </datascroll>
  <datascroll>
    <ユーザーNO>1048</ユーザーNO>
    <姓>郡司</姓>
    <名>由美</名>
    <姓_カタカナ>グンジ</姓_カタカナ>
    <名_カタカナ>ユミ</名_カタカナ>
    <性別>女</性別>
    <電話番号>0887896163</電話番号>
    <メールアドレス>Yumi_Gunji@mtglwirgev.rtn</メールアドレス>
    <郵便番号>786-0027</郵便番号>
    <現住所_県>高知県</現住所_県>
    <現住所_市>高岡郡四万十町</現住所_市>
    <生年月日>1958/02/21</生年月日>
    <年齢>57</年齢>
    <出身地>徳島県</出身地>
    <血液型>B</血液型>
  </datascroll>
  <datascroll>
    <ユーザーNO>1049</ユーザーNO>
    <姓>細谷</姓>
    <名>孝一</名>
    <姓_カタカナ>ホソヤ</姓_カタカナ>
    <名_カタカナ>コウイチ</名_カタカナ>
    <性別>男</性別>
    <電話番号>0985341279</電話番号>
    <メールアドレス>vupcri=ksxbev=hkouichi30288@caxbvok.gss</メールアドレス>
    <郵便番号>880-0005</郵便番号>
    <現住所_県>宮崎県</現住所_県>
    <現住所_市>宮崎市</現住所_市>
    <生年月日>1964/02/26</生年月日>
    <年齢>51</年齢>
    <出身地>京都府</出身地>
    <血液型>A</血液型>
  </datascroll>
  <datascroll>
    <ユーザーNO>1050</ユーザーNO>
    <姓>坂上</姓>
    <名>浩子</名>
    <姓_カタカナ>サカガミ</姓_カタカナ>
    <名_カタカナ>ヒロコ</名_カタカナ>
    <性別>女</性別>
    <電話番号>0520821575</電話番号>
    <メールアドレス>hiroko61707@zhngrqbbs.tda</メールアドレス>
    <郵便番号>496-0036</郵便番号>
    <現住所_県>愛知県</現住所_県>
    <現住所_市>津島市</現住所_市>
    <生年月日>1955/11/12</生年月日>
    <年齢>59</年齢>
    <出身地>富山県</出身地>
    <血液型>O</血液型>
  </datascroll>
  <datascroll>
    <ユーザーNO>1051</ユーザーNO>
    <姓>比嘉</姓>
    <名>百合子</名>
    <姓_カタカナ>ヒガ</姓_カタカナ>
    <名_カタカナ>ユリコ</名_カタカナ>
    <性別>女</性別>
    <電話番号>0465057386</電話番号>
    <メールアドレス>isruuobtyuriko57963@dhml.mxq</メールアドレス>
    <郵便番号>343-0814</郵便番号>
    <現住所_県>埼玉県</現住所_県>
    <現住所_市>越谷市</現住所_市>
    <生年月日>1974/10/04</生年月日>
    <年齢>40</年齢>
    <出身地>三重県</出身地>
    <血液型>A</血液型>
  </datascroll>
  <datascroll>
    <ユーザーNO>1052</ユーザーNO>
    <姓>重田</姓>
    <名>茜</名>
    <姓_カタカナ>シゲタ</姓_カタカナ>
    <名_カタカナ>アカネ</名_カタカナ>
    <性別>女</性別>
    <電話番号>0220138794</電話番号>
    <メールアドレス>akane55715@cogjqiqdy.li.rxd</メールアドレス>
    <郵便番号>981-3124</郵便番号>
    <現住所_県>宮城県</現住所_県>
    <現住所_市>仙台市泉区</現住所_市>
    <生年月日>1956/05/09</生年月日>
    <年齢>59</年齢>
    <出身地>山梨県</出身地>
    <血液型>O</血液型>
  </datascroll>
  <datascroll>
    <ユーザーNO>1053</ユーザーNO>
    <姓>小野田</姓>
    <名>初江</名>
    <姓_カタカナ>オノダ</姓_カタカナ>
    <名_カタカナ>ハツエ</名_カタカナ>
    <性別>女</性別>
    <電話番号>0820098202</電話番号>
    <メールアドレス>eonoda@ybkkpkjtio.iknud.aq</メールアドレス>
    <郵便番号>751-0846</郵便番号>
    <現住所_県>山口県</現住所_県>
    <現住所_市>下関市</現住所_市>
    <生年月日>1959/12/05</生年月日>
    <年齢>55</年齢>
    <出身地>埼玉県</出身地>
    <血液型>O</血液型>
  </datascroll>
  <datascroll>
    <ユーザーNO>1054</ユーザーNO>
    <姓>大塚</姓>
    <名>百香</名>
    <姓_カタカナ>オオツカ</姓_カタカナ>
    <名_カタカナ>モモカ</名_カタカナ>
    <性別>女</性別>
    <電話番号>0887965503</電話番号>
    <メールアドレス>momoka6594@qmzqn.lbu</メールアドレス>
    <郵便番号>787-1325</郵便番号>
    <現住所_県>高知県</現住所_県>
    <現住所_市>四万十市</現住所_市>
    <生年月日>1959/09/09</生年月日>
    <年齢>55</年齢>
    <出身地>山梨県</出身地>
    <血液型>B</血液型>
  </datascroll>
  <datascroll>
    <ユーザーNO>1055</ユーザーNO>
    <姓>相原</姓>
    <名>仁一</名>
    <姓_カタカナ>アイハラ</姓_カタカナ>
    <名_カタカナ>ジンイチ</名_カタカナ>
    <性別>男</性別>
    <電話番号>0968743530</電話番号>
    <メールアドレス>jinichi5056@dmbz.fco.nxt</メールアドレス>
    <郵便番号>861-4634</郵便番号>
    <現住所_県>熊本県</現住所_県>
    <現住所_市>上益城郡甲佐町</現住所_市>
    <生年月日>1975/08/17</生年月日>
    <年齢>39</年齢>
    <出身地>和歌山県</出身地>
    <血液型>B</血液型>
  </datascroll>
  <datascroll>
    <ユーザーNO>1056</ユーザーNO>
    <姓>相原</姓>
    <名>七美</名>
    <姓_カタカナ>アイハラ</姓_カタカナ>
    <名_カタカナ>ナナミ</名_カタカナ>
    <性別>女</性別>
    <電話番号>0991971886</電話番号>
    <メールアドレス>Nanami_Aihara@yokcxgh.rmh</メールアドレス>
    <郵便番号>891-0103</郵便番号>
    <現住所_県>鹿児島県</現住所_県>
    <現住所_市>鹿児島市</現住所_市>
    <生年月日>1965/04/17</生年月日>
    <年齢>50</年齢>
    <出身地>鳥取県</出身地>
    <血液型>B</血液型>
  </datascroll>
  <datascroll>
    <ユーザーNO>1057</ユーザーNO>
    <姓>筒井</姓>
    <名>忠三</名>
    <姓_カタカナ>ツツイ</姓_カタカナ>
    <名_カタカナ>チュウゾウ</名_カタカナ>
    <性別>男</性別>
    <電話番号>0970392454</電話番号>
    <メールアドレス>rkkkbeykojobchuuzou65031@fdvufryh.lut</メールアドレス>
    <郵便番号>870-0006</郵便番号>
    <現住所_県>大分県</現住所_県>
    <現住所_市>大分市</現住所_市>
    <生年月日>1993/09/07</生年月日>
    <年齢>21</年齢>
    <出身地>神奈川県</出身地>
    <血液型>A</血液型>
  </datascroll>
  <datascroll>
    <ユーザーNO>1058</ユーザーNO>
    <姓>笹川</姓>
    <名>菜那</名>
    <姓_カタカナ>ササガワ</姓_カタカナ>
    <名_カタカナ>ナナ</名_カタカナ>
    <性別>女</性別>
    <電話番号>0237256958</電話番号>
    <メールアドレス>nana_sasagawa@sbyc.mtk.dd</メールアドレス>
    <郵便番号>999-4553</郵便番号>
    <現住所_県>山形県</現住所_県>
    <現住所_市>尾花沢市</現住所_市>
    <生年月日>1972/11/18</生年月日>
    <年齢>42</年齢>
    <出身地>兵庫県</出身地>
    <血液型>A</血液型>
  </datascroll>
  <datascroll>
    <ユーザーNO>1059</ユーザーNO>
    <姓>須田</姓>
    <名>兼吉</名>
    <姓_カタカナ>スダ</姓_カタカナ>
    <名_カタカナ>カネキチ</名_カタカナ>
    <性別>男</性別>
    <電話番号>0267848379</電話番号>
    <メールアドレス>Kanekichi_Suda@tyjq.aba</メールアドレス>
    <郵便番号>382-0016</郵便番号>
    <現住所_県>長野県</現住所_県>
    <現住所_市>須坂市</現住所_市>
    <生年月日>1963/04/30</生年月日>
    <年齢>52</年齢>
    <出身地>千葉県</出身地>
    <血液型>AB</血液型>
  </datascroll>
  <datascroll>
    <ユーザーNO>1060</ユーザーNO>
    <姓>野間</姓>
    <名>朱里</名>
    <姓_カタカナ>ノマ</姓_カタカナ>
    <名_カタカナ>アカリ</名_カタカナ>
    <性別>女</性別>
    <電話番号>0957777505</電話番号>
    <メールアドレス>inoma@ndrh.cgk</メールアドレス>
    <郵便番号>850-0917</郵便番号>
    <現住所_県>長崎県</現住所_県>
    <現住所_市>長崎市</現住所_市>
    <生年月日>1973/12/04</生年月日>
    <年齢>41</年齢>
    <出身地>山梨県</出身地>
    <血液型>B</血液型>
  </datascroll>
  <datascroll>
    <ユーザーNO>1061</ユーザーNO>
    <姓>小野田</姓>
    <名>舞花</名>
    <姓_カタカナ>オノダ</姓_カタカナ>
    <名_カタカナ>マイカ</名_カタカナ>
    <性別>女</性別>
    <電話番号>0846134131</電話番号>
    <メールアドレス>z=xulymaika25969@yzygp.tcw</メールアドレス>
    <郵便番号>739-0403</郵便番号>
    <現住所_県>広島県</現住所_県>
    <現住所_市>廿日市市</現住所_市>
    <生年月日>1990/02/23</生年月日>
    <年齢>25</年齢>
    <出身地>神奈川県</出身地>
    <血液型>A</血液型>
  </datascroll>
  <datascroll>
    <ユーザーNO>1062</ユーザーNO>
    <姓>手島</姓>
    <名>裕美</名>
    <姓_カタカナ>テジマ</姓_カタカナ>
    <名_カタカナ>ヒロミ</名_カタカナ>
    <性別>女</性別>
    <電話番号>0195158816</電話番号>
    <メールアドレス>hiromi31737@kczpicr.bnb</メールアドレス>
    <郵便番号>020-0826</郵便番号>
    <現住所_県>岩手県</現住所_県>
    <現住所_市>盛岡市</現住所_市>
    <生年月日>1965/12/12</生年月日>
    <年齢>49</年齢>
    <出身地>宮崎県</出身地>
    <血液型>A</血液型>
  </datascroll>
  <datascroll>
    <ユーザーNO>1063</ユーザーNO>
    <姓>三宅</姓>
    <名>真生</名>
    <姓_カタカナ>ミヤケ</姓_カタカナ>
    <名_カタカナ>マオ</名_カタカナ>
    <性別>女</性別>
    <電話番号>0171889876</電話番号>
    <メールアドレス>gg-fkntyxkgmao3986@izohplkrx.apb</メールアドレス>
    <郵便番号>038-2201</郵便番号>
    <現住所_県>青森県</現住所_県>
    <現住所_市>西津軽郡深浦町</現住所_市>
    <生年月日>1985/01/27</生年月日>
    <年齢>30</年齢>
    <出身地>山形県</出身地>
    <血液型>AB</血液型>
  </datascroll>
  <datascroll>
    <ユーザーNO>1064</ユーザーNO>
    <姓>冨田</姓>
    <名>志郎</名>
    <姓_カタカナ>トミタ</姓_カタカナ>
    <名_カタカナ>シロウ</名_カタカナ>
    <性別>男</性別>
    <電話番号>086525836</電話番号>
    <メールアドレス>shiroutomita@ypmbmott.ir</メールアドレス>
    <郵便番号>717-0405</郵便番号>
    <現住所_県>岡山県</現住所_県>
    <現住所_市>真庭市</現住所_市>
    <生年月日>1957/05/19</生年月日>
    <年齢>58</年齢>
    <出身地>三重県</出身地>
    <血液型>O</血液型>
  </datascroll>
  <datascroll>
    <ユーザーNO>1065</ユーザーNO>
    <姓>長沢</姓>
    <名>鈴子</名>
    <姓_カタカナ>ナガサワ</姓_カタカナ>
    <名_カタカナ>スズコ</名_カタカナ>
    <性別>女</性別>
    <電話番号>0893388430</電話番号>
    <メールアドレス>suzuko08018@vbmx.tyu</メールアドレス>
    <郵便番号>798-2106</郵便番号>
    <現住所_県>愛媛県</現住所_県>
    <現住所_市>北宇和郡松野町</現住所_市>
    <生年月日>1991/06/22</生年月日>
    <年齢>24</年齢>
    <出身地>長野県</出身地>
    <血液型>B</血液型>
  </datascroll>
  <datascroll>
    <ユーザーNO>1066</ユーザーNO>
    <姓>影山</姓>
    <名>稟</名>
    <姓_カタカナ>カゲヤマ</姓_カタカナ>
    <名_カタカナ>リン</名_カタカナ>
    <性別>女</性別>
    <電話番号>0295391072</電話番号>
    <メールアドレス>rin1942@ckyeys.rdthv.ol</メールアドレス>
    <郵便番号>311-1406</郵便番号>
    <現住所_県>茨城県</現住所_県>
    <現住所_市>鉾田市</現住所_市>
    <生年月日>1969/06/26</生年月日>
    <年齢>46</年齢>
    <出身地>岐阜県</出身地>
    <血液型>A</血液型>
  </datascroll>
  <datascroll>
    <ユーザーNO>1067</ユーザーNO>
    <姓>佐野</姓>
    <名>研一</名>
    <姓_カタカナ>サノ</姓_カタカナ>
    <名_カタカナ>ケンイチ</名_カタカナ>
    <性別>男</性別>
    <電話番号>0930148393</電話番号>
    <メールアドレス>Kenichi_Sano@esdgrls.eo</メールアドレス>
    <郵便番号>801-0812</郵便番号>
    <現住所_県>福岡県</現住所_県>
    <現住所_市>北九州市門司区</現住所_市>
    <生年月日>1993/05/20</生年月日>
    <年齢>22</年齢>
    <出身地>東京都</出身地>
    <血液型>A</血液型>
  </datascroll>
  <datascroll>
    <ユーザーNO>1068</ユーザーNO>
    <姓>松島</姓>
    <名>丈人</名>
    <姓_カタカナ>マツシマ</姓_カタカナ>
    <名_カタカナ>タケト</名_カタカナ>
    <性別>男</性別>
    <電話番号>0984297786</電話番号>
    <メールアドレス>taketomatsushima@peagwpxb.jkmsv.ba</メールアドレス>
    <郵便番号>904-2244</郵便番号>
    <現住所_県>沖縄県</現住所_県>
    <現住所_市>うるま市</現住所_市>
    <生年月日>1967/02/27</生年月日>
    <年齢>48</年齢>
    <出身地>富山県</出身地>
    <血液型>A</血液型>
  </datascroll>
  <datascroll>
    <ユーザーNO>1069</ユーザーNO>
    <姓>西原</姓>
    <名>秀樹</名>
    <姓_カタカナ>ニシハラ</姓_カタカナ>
    <名_カタカナ>ヒデキ</名_カタカナ>
    <性別>男</性別>
    <電話番号>0857307011</電話番号>
    <メールアドレス>hideki128@bcgxyrpc.eb.yu</メールアドレス>
    <郵便番号>689-1442</郵便番号>
    <現住所_県>鳥取県</現住所_県>
    <現住所_市>八頭郡智頭町</現住所_市>
    <生年月日>1968/11/09</生年月日>
    <年齢>46</年齢>
    <出身地>新潟県</出身地>
    <血液型>A</血液型>
  </datascroll>
  <datascroll>
    <ユーザーNO>1070</ユーザーNO>
    <姓>迫田</姓>
    <名>一子</名>
    <姓_カタカナ>サコタ</姓_カタカナ>
    <名_カタカナ>イチコ</名_カタカナ>
    <性別>女</性別>
    <電話番号>0934127285</電話番号>
    <メールアドレス>ichiko677@nmjay.bq.ch</メールアドレス>
    <郵便番号>839-0861</郵便番号>
    <現住所_県>福岡県</現住所_県>
    <現住所_市>久留米市</現住所_市>
    <生年月日>1995/07/15</生年月日>
    <年齢>20</年齢>
    <出身地>熊本県</出身地>
    <血液型>O</血液型>
  </datascroll>
  <datascroll>
    <ユーザーNO>1071</ユーザーNO>
    <姓>石原</姓>
    <名>広行</名>
    <姓_カタカナ>イシハラ</姓_カタカナ>
    <名_カタカナ>ヒロユキ</名_カタカナ>
    <性別>男</性別>
    <電話番号>0197598915</電話番号>
    <メールアドレス>hiroyuki_ishihara@ziyylk.sms.hvo</メールアドレス>
    <郵便番号>023-0084</郵便番号>
    <現住所_県>岩手県</現住所_県>
    <現住所_市>奥州市</現住所_市>
    <生年月日>1988/08/13</生年月日>
    <年齢>26</年齢>
    <出身地>大阪府</出身地>
    <血液型>AB</血液型>
  </datascroll>
  <datascroll>
    <ユーザーNO>1072</ユーザーNO>
    <姓>神山</姓>
    <名>七菜</名>
    <姓_カタカナ>カミヤマ</姓_カタカナ>
    <名_カタカナ>ナナ</名_カタカナ>
    <性別>女</性別>
    <電話番号>017891344</電話番号>
    <メールアドレス>nana8740@pwsjvhpr.jxu.ac</メールアドレス>
    <郵便番号>039-3381</郵便番号>
    <現住所_県>青森県</現住所_県>
    <現住所_市>東津軽郡平内町</現住所_市>
    <生年月日>1985/12/08</生年月日>
    <年齢>29</年齢>
    <出身地>高知県</出身地>
    <血液型>O</血液型>
  </datascroll>
  <datascroll>
    <ユーザーNO>1073</ユーザーNO>
    <姓>田淵</姓>
    <名>敦盛</名>
    <姓_カタカナ>タブチ</姓_カタカナ>
    <名_カタカナ>アツモリ</名_カタカナ>
    <性別>男</性別>
    <電話番号>0194580386</電話番号>
    <メールアドレス>uvmbwlatsumori20921@xgikqkguy.roq</メールアドレス>
    <郵便番号>028-5306</郵便番号>
    <現住所_県>岩手県</現住所_県>
    <現住所_市>二戸郡一戸町</現住所_市>
    <生年月日>1985/02/12</生年月日>
    <年齢>30</年齢>
    <出身地>鹿児島県</出身地>
    <血液型>A</血液型>
  </datascroll>
  <datascroll>
    <ユーザーNO>1074</ユーザーNO>
    <姓>内田</姓>
    <名>俊郎</名>
    <姓_カタカナ>ウチダ</姓_カタカナ>
    <名_カタカナ>トシロウ</名_カタカナ>
    <性別>男</性別>
    <電話番号>045462452</電話番号>
    <メールアドレス>uuchida@vglm.kw.quk</メールアドレス>
    <郵便番号>220-0002</郵便番号>
    <現住所_県>神奈川県</現住所_県>
    <現住所_市>横浜市西区</現住所_市>
    <生年月日>1983/06/26</生年月日>
    <年齢>32</年齢>
    <出身地>宮城県</出身地>
    <血液型>O</血液型>
  </datascroll>
  <datascroll>
    <ユーザーNO>1075</ユーザーNO>
    <姓>東山</姓>
    <名>静香</名>
    <姓_カタカナ>ヒガシヤマ</姓_カタカナ>
    <名_カタカナ>シズカ</名_カタカナ>
    <性別>女</性別>
    <電話番号>0883399715</電話番号>
    <メールアドレス>ahigashiyama@zzannupof.koc</メールアドレス>
    <郵便番号>779-5171</郵便番号>
    <現住所_県>徳島県</現住所_県>
    <現住所_市>三好市</現住所_市>
    <生年月日>1985/06/18</生年月日>
    <年齢>30</年齢>
    <出身地>神奈川県</出身地>
    <血液型>A</血液型>
  </datascroll>
  <datascroll>
    <ユーザーNO>1076</ユーザーNO>
    <姓>新川</姓>
    <名>直吉</名>
    <姓_カタカナ>シンカワ</姓_カタカナ>
    <名_カタカナ>ナオキチ</名_カタカナ>
    <性別>男</性別>
    <電話番号>0776641228</電話番号>
    <メールアドレス>ishinkawa@ufwouajqt.qi</メールアドレス>
    <郵便番号>615-8181</郵便番号>
    <現住所_県>京都府</現住所_県>
    <現住所_市>京都市西京区</現住所_市>
    <生年月日>1965/05/03</生年月日>
    <年齢>50</年齢>
    <出身地>滋賀県</出身地>
    <血液型>A</血液型>
  </datascroll>
  <datascroll>
    <ユーザーNO>1077</ユーザーNO>
    <姓>石塚</姓>
    <名>美結</名>
    <姓_カタカナ>イシヅカ</姓_カタカナ>
    <名_カタカナ>ミユ</名_カタカナ>
    <性別>女</性別>
    <電話番号>0980401335</電話番号>
    <メールアドレス>miyu57512@bkyfoku.lu</メールアドレス>
    <郵便番号>905-1147</郵便番号>
    <現住所_県>沖縄県</現住所_県>
    <現住所_市>名護市</現住所_市>
    <生年月日>1961/06/30</生年月日>
    <年齢>54</年齢>
    <出身地>香川県</出身地>
    <血液型>A</血液型>
  </datascroll>
  <datascroll>
    <ユーザーNO>1078</ユーザーNO>
    <姓>依田</姓>
    <名>正三</名>
    <姓_カタカナ>イダ</姓_カタカナ>
    <名_カタカナ>ショウゾウ</名_カタカナ>
    <性別>男</性別>
    <電話番号>0964723556</電話番号>
    <メールアドレス>shouzou9791@apzie.msh.mi</メールアドレス>
    <郵便番号>860-0806</郵便番号>
    <現住所_県>熊本県</現住所_県>
    <現住所_市>熊本市</現住所_市>
    <生年月日>1957/12/01</生年月日>
    <年齢>57</年齢>
    <出身地>静岡県</出身地>
    <血液型>A</血液型>
  </datascroll>
  <datascroll>
    <ユーザーNO>1079</ユーザーNO>
    <姓>瀬戸</姓>
    <名>喜久雄</名>
    <姓_カタカナ>セト</姓_カタカナ>
    <名_カタカナ>キクオ</名_カタカナ>
    <性別>男</性別>
    <電話番号>0742448787</電話番号>
    <メールアドレス>kikuo_seto@wrictxgulr.awn.tq</メールアドレス>
    <郵便番号>639-1035</郵便番号>
    <現住所_県>奈良県</現住所_県>
    <現住所_市>大和郡山市</現住所_市>
    <生年月日>1984/12/29</生年月日>
    <年齢>30</年齢>
    <出身地>長崎県</出身地>
    <血液型>A</血液型>
  </datascroll>
  <datascroll>
    <ユーザーNO>1080</ユーザーNO>
    <姓>白川</姓>
    <名>麗香</名>
    <姓_カタカナ>シラカワ</姓_カタカナ>
    <名_カタカナ>レイカ</名_カタカナ>
    <性別>女</性別>
    <電話番号>0978524987</電話番号>
    <メールアドレス>ashirakawa@bjurbm.iiv</メールアドレス>
    <郵便番号>879-5423</郵便番号>
    <現住所_県>大分県</現住所_県>
    <現住所_市>由布市</現住所_市>
    <生年月日>1984/03/08</生年月日>
    <年齢>31</年齢>
    <出身地>大阪府</出身地>
    <血液型>O</血液型>
  </datascroll>
  <datascroll>
    <ユーザーNO>1081</ユーザーNO>
    <姓>富永</姓>
    <名>南</名>
    <姓_カタカナ>トミナガ</姓_カタカナ>
    <名_カタカナ>ミナミ</名_カタカナ>
    <性別>女</性別>
    <電話番号>0765198761</電話番号>
    <メールアドレス>minami_tominaga@nysbysvql.mc</メールアドレス>
    <郵便番号>939-1362</郵便番号>
    <現住所_県>富山県</現住所_県>
    <現住所_市>砺波市</現住所_市>
    <生年月日>1983/02/04</生年月日>
    <年齢>32</年齢>
    <出身地>岡山県</出身地>
    <血液型>O</血液型>
  </datascroll>
  <datascroll>
    <ユーザーNO>1082</ユーザーNO>
    <姓>大倉</姓>
    <名>三雄</名>
    <姓_カタカナ>オオクラ</姓_カタカナ>
    <名_カタカナ>ミツオ</名_カタカナ>
    <性別>男</性別>
    <電話番号>0353774089</電話番号>
    <メールアドレス>mitsuo67712@pqaoze.wp.vs</メールアドレス>
    <郵便番号>101-0061</郵便番号>
    <現住所_県>東京都</現住所_県>
    <現住所_市>千代田区</現住所_市>
    <生年月日>1958/05/15</生年月日>
    <年齢>57</年齢>
    <出身地>徳島県</出身地>
    <血液型>O</血液型>
  </datascroll>
  <datascroll>
    <ユーザーNO>1083</ユーザーNO>
    <姓>平本</姓>
    <名>廣祐</名>
    <姓_カタカナ>ヒラモト</姓_カタカナ>
    <名_カタカナ>コウスケ</名_カタカナ>
    <性別>男</性別>
    <電話番号>0594704117</電話番号>
    <メールアドレス>kousuke3490@krinzw.gh</メールアドレス>
    <郵便番号>513-0007</郵便番号>
    <現住所_県>三重県</現住所_県>
    <現住所_市>鈴鹿市</現住所_市>
    <生年月日>1965/05/20</生年月日>
    <年齢>50</年齢>
    <出身地>宮崎県</出身地>
    <血液型>A</血液型>
  </datascroll>
  <datascroll>
    <ユーザーNO>1084</ユーザーNO>
    <姓>金野</姓>
    <名>利彦</名>
    <姓_カタカナ>カネノ</姓_カタカナ>
    <名_カタカナ>トシヒコ</名_カタカナ>
    <性別>男</性別>
    <電話番号>0967415130</電話番号>
    <メールアドレス>toshihikokaneno@oyneclotlc.dtq</メールアドレス>
    <郵便番号>869-0631</郵便番号>
    <現住所_県>熊本県</現住所_県>
    <現住所_市>宇城市</現住所_市>
    <生年月日>1989/09/10</生年月日>
    <年齢>25</年齢>
    <出身地>福井県</出身地>
    <血液型>AB</血液型>
  </datascroll>
  <datascroll>
    <ユーザーNO>1085</ユーザーNO>
    <姓>鮫島</姓>
    <名>哲美</名>
    <姓_カタカナ>サメジマ</姓_カタカナ>
    <名_カタカナ>テツミ</名_カタカナ>
    <性別>女</性別>
    <電話番号>0287967700</電話番号>
    <メールアドレス>tetsumisamejima@vkmvpv.sk</メールアドレス>
    <郵便番号>324-0022</郵便番号>
    <現住所_県>栃木県</現住所_県>
    <現住所_市>大田原市</現住所_市>
    <生年月日>1965/05/01</生年月日>
    <年齢>50</年齢>
    <出身地>茨城県</出身地>
    <血液型>A</血液型>
  </datascroll>
  <datascroll>
    <ユーザーNO>1086</ユーザーNO>
    <姓>神田</姓>
    <名>真結</名>
    <姓_カタカナ>カンダ</姓_カタカナ>
    <名_カタカナ>マユ</名_カタカナ>
    <性別>女</性別>
    <電話番号>0584977702</電話番号>
    <メールアドレス>ukanda@udgnz.td</メールアドレス>
    <郵便番号>509-0230</郵便番号>
    <現住所_県>岐阜県</現住所_県>
    <現住所_市>可児市</現住所_市>
    <生年月日>1959/07/30</生年月日>
    <年齢>56</年齢>
    <出身地>愛知県</出身地>
    <血液型>O</血液型>
  </datascroll>
  <datascroll>
    <ユーザーNO>1087</ユーザーNO>
    <姓>皆川</姓>
    <名>千鶴</名>
    <姓_カタカナ>ミナガワ</姓_カタカナ>
    <名_カタカナ>チヅル</名_カタカナ>
    <性別>女</性別>
    <電話番号>0565502997</電話番号>
    <メールアドレス>chizuru659@miykhqi.bcfx.xwe</メールアドレス>
    <郵便番号>484-0901</郵便番号>
    <現住所_県>愛知県</現住所_県>
    <現住所_市>犬山市</現住所_市>
    <生年月日>1995/07/13</生年月日>
    <年齢>20</年齢>
    <出身地>山梨県</出身地>
    <血液型>AB</血液型>
  </datascroll>
  <datascroll>
    <ユーザーNO>1088</ユーザーNO>
    <姓>下村</姓>
    <名>翼</名>
    <姓_カタカナ>シモムラ</姓_カタカナ>
    <名_カタカナ>ツバサ</名_カタカナ>
    <性別>男</性別>
    <電話番号>0826345908</電話番号>
    <メールアドレス>tsubasa420@kxsgxpcf.awt</メールアドレス>
    <郵便番号>722-1514</郵便番号>
    <現住所_県>広島県</現住所_県>
    <現住所_市>三原市</現住所_市>
    <生年月日>1989/03/08</生年月日>
    <年齢>26</年齢>
    <出身地>石川県</出身地>
    <血液型>B</血液型>
  </datascroll>
  <datascroll>
    <ユーザーNO>1089</ユーザーNO>
    <姓>平良</姓>
    <名>政行</名>
    <姓_カタカナ>ヒラヨシ</姓_カタカナ>
    <名_カタカナ>マサユキ</名_カタカナ>
    <性別>男</性別>
    <電話番号>0240838733</電話番号>
    <メールアドレス>Masayuki_Hirayoshi@kmhgghhgec.kty.ob</メールアドレス>
    <郵便番号>969-6274</郵便番号>
    <現住所_県>福島県</現住所_県>
    <現住所_市>大沼郡会津美里町</現住所_市>
    <生年月日>1994/07/03</生年月日>
    <年齢>21</年齢>
    <出身地>三重県</出身地>
    <血液型>O</血液型>
  </datascroll>
  <datascroll>
    <ユーザーNO>1090</ユーザーNO>
    <姓>西山</姓>
    <名>忠三</名>
    <姓_カタカナ>ニシヤマ</姓_カタカナ>
    <名_カタカナ>チュウゾウ</名_カタカナ>
    <性別>男</性別>
    <電話番号>0550173956</電話番号>
    <メールアドレス>chuuzou28397@oupwdg.tn</メールアドレス>
    <郵便番号>404-0033</郵便番号>
    <現住所_県>山梨県</現住所_県>
    <現住所_市>甲州市</現住所_市>
    <生年月日>1959/06/29</生年月日>
    <年齢>56</年齢>
    <出身地>石川県</出身地>
    <血液型>O</血液型>
  </datascroll>
  <datascroll>
    <ユーザーNO>1091</ユーザーNO>
    <姓>田村</姓>
    <名>仁美</名>
    <姓_カタカナ>タムラ</姓_カタカナ>
    <名_カタカナ>ヒトミ</名_カタカナ>
    <性別>女</性別>
    <電話番号>025171606</電話番号>
    <メールアドレス>Hitomi_Tamura@crrouvzp.ry</メールアドレス>
    <郵便番号>949-5123</郵便番号>
    <現住所_県>新潟県</現住所_県>
    <現住所_市>長岡市</現住所_市>
    <生年月日>1981/01/17</生年月日>
    <年齢>34</年齢>
    <出身地>石川県</出身地>
    <血液型>B</血液型>
  </datascroll>
  <datascroll>
    <ユーザーNO>1092</ユーザーNO>
    <姓>有田</姓>
    <名>敦彦</名>
    <姓_カタカナ>アリタ</姓_カタカナ>
    <名_カタカナ>アツヒコ</名_カタカナ>
    <性別>男</性別>
    <電話番号>0233618049</電話番号>
    <メールアドレス>atsuhiko237@uuecdkxgaz.zgu.gh</メールアドレス>
    <郵便番号>999-7762</郵便番号>
    <現住所_県>山形県</現住所_県>
    <現住所_市>東田川郡庄内町</現住所_市>
    <生年月日>1982/11/25</生年月日>
    <年齢>32</年齢>
    <出身地>熊本県</出身地>
    <血液型>A</血液型>
  </datascroll>
  <datascroll>
    <ユーザーNO>1093</ユーザーNO>
    <姓>竹本</姓>
    <名>蒼衣</名>
    <姓_カタカナ>タケモト</姓_カタカナ>
    <名_カタカナ>アオイ</名_カタカナ>
    <性別>女</性別>
    <電話番号>0785387911</電話番号>
    <メールアドレス>itakemoto@yyudewsau.op</メールアドレス>
    <郵便番号>675-1379</郵便番号>
    <現住所_県>兵庫県</現住所_県>
    <現住所_市>小野市</現住所_市>
    <生年月日>1981/05/21</生年月日>
    <年齢>34</年齢>
    <出身地>青森県</出身地>
    <血液型>O</血液型>
  </datascroll>
  <datascroll>
    <ユーザーNO>1094</ユーザーNO>
    <姓>桑原</姓>
    <名>勝男</名>
    <姓_カタカナ>クハバラ</姓_カタカナ>
    <名_カタカナ>カツオ</名_カタカナ>
    <性別>男</性別>
    <電話番号>0863565539</電話番号>
    <メールアドレス>katsuo966@vaogey.gh</メールアドレス>
    <郵便番号>707-0035</郵便番号>
    <現住所_県>岡山県</現住所_県>
    <現住所_市>美作市</現住所_市>
    <生年月日>1984/02/05</生年月日>
    <年齢>31</年齢>
    <出身地>大阪府</出身地>
    <血液型>A</血液型>
  </datascroll>
  <datascroll>
    <ユーザーNO>1095</ユーザーNO>
    <姓>上山</姓>
    <名>郁子</名>
    <姓_カタカナ>カミヤマ</姓_カタカナ>
    <名_カタカナ>イクコ</名_カタカナ>
    <性別>女</性別>
    <電話番号>0883959511</電話番号>
    <メールアドレス>ikuko35841@hzjuc.qyccx.lnh</メールアドレス>
    <郵便番号>781-2144</郵便番号>
    <現住所_県>高知県</現住所_県>
    <現住所_市>吾川郡いの町</現住所_市>
    <生年月日>1976/03/22</生年月日>
    <年齢>39</年齢>
    <出身地>茨城県</出身地>
    <血液型>A</血液型>
  </datascroll>
  <datascroll>
    <ユーザーNO>1096</ユーザーNO>
    <姓>垣内</姓>
    <名>美希</名>
    <姓_カタカナ>カキウチ</姓_カタカナ>
    <名_カタカナ>ミキ</名_カタカナ>
    <性別>女</性別>
    <電話番号>0875678140</電話番号>
    <メールアドレス>btmwauvebaymiki115@odyh.lry</メールアドレス>
    <郵便番号>761-2206</郵便番号>
    <現住所_県>香川県</現住所_県>
    <現住所_市>綾歌郡綾川町</現住所_市>
    <生年月日>1973/01/19</生年月日>
    <年齢>42</年齢>
    <出身地>静岡県</出身地>
    <血液型>A</血液型>
  </datascroll>
  <datascroll>
    <ユーザーNO>1097</ユーザーNO>
    <姓>関</姓>
    <名>美佐子</名>
    <姓_カタカナ>カン</姓_カタカナ>
    <名_カタカナ>ミサコ</名_カタカナ>
    <性別>女</性別>
    <電話番号>0248758601</電話番号>
    <メールアドレス>misako95931@ptnzdcbzf.zg</メールアドレス>
    <郵便番号>969-6553</郵便番号>
    <現住所_県>福島県</現住所_県>
    <現住所_市>河沼郡会津坂下町</現住所_市>
    <生年月日>1963/12/05</生年月日>
    <年齢>51</年齢>
    <出身地>愛知県</出身地>
    <血液型>O</血液型>
  </datascroll>
  <datascroll>
    <ユーザーNO>1098</ユーザーNO>
    <姓>川添</姓>
    <名>一彦</名>
    <姓_カタカナ>カワゾエ</姓_カタカナ>
    <名_カタカナ>カズヒコ</名_カタカナ>
    <性別>男</性別>
    <電話番号>0791471349</電話番号>
    <メールアドレス>Kazuhiko_Kawazoe@btmh.ff.bs</メールアドレス>
    <郵便番号>667-1522</郵便番号>
    <現住所_県>兵庫県</現住所_県>
    <現住所_市>美方郡香美町</現住所_市>
    <生年月日>1984/05/19</生年月日>
    <年齢>31</年齢>
    <出身地>高知県</出身地>
    <血液型>O</血液型>
  </datascroll>
  <datascroll>
    <ユーザーNO>1099</ユーザーNO>
    <姓>大林</姓>
    <名>孝志</名>
    <姓_カタカナ>オオバヤシ</姓_カタカナ>
    <名_カタカナ>タカシ</名_カタカナ>
    <性別>男</性別>
    <電話番号>0826771759</電話番号>
    <メールアドレス>takashi834@lksti.bw</メールアドレス>
    <郵便番号>727-0425</郵便番号>
    <現住所_県>広島県</現住所_県>
    <現住所_市>庄原市</現住所_市>
    <生年月日>1967/07/07</生年月日>
    <年齢>48</年齢>
    <出身地>石川県</出身地>
    <血液型>B</血液型>
  </datascroll>
  <datascroll>
    <ユーザーNO>1100</ユーザーNO>
    <姓>向井</姓>
    <名>蓮</名>
    <姓_カタカナ>ムカイ</姓_カタカナ>
    <名_カタカナ>レン</名_カタカナ>
    <性別>女</性別>
    <電話番号>0585946250</電話番号>
    <メールアドレス>Ren_Mukai@pjao.oq</メールアドレス>
    <郵便番号>503-2315</郵便番号>
    <現住所_県>岐阜県</現住所_県>
    <現住所_市>安八郡神戸町</現住所_市>
    <生年月日>1967/11/26</生年月日>
    <年齢>47</年齢>
    <出身地>京都府</出身地>
    <血液型>O</血液型>
  </datascroll>
</datascrolls>